{
    "case_id": "",
    "court": "",
    "date": "",
    "judge": "",
    "petitioners": [],
    "respondents": [],
    "sections": [],
    "outcome": "",
    "full_text": "IN THE COURT OF JUDICIAL MAGISTRATE OF THE FIRST CLASS- TI\nTHIRUVANANTHAPURAM\nPresent: Sri. Vinod Babu M.U\nJudicial Magistrate of the First Class-III\nFriday 15\" day of February, 2025\nCG. 1489/2020\nComplainant : State represented by the Sub Inspector of Police,\nMuseum Police Station ( Museum Crime 482/20).\n(By Asst. Public Prosecutor)\nAccused : Suraj, aged 19/20 years, S/o Suresh Kumar, Chaithanya\nveedu, Ganapathiyamkodu ward, Chayam, Tholikkodu\nvillage.\n(ByAdv. Sri.Sakkir Husain. M)\nOffences : Ufs. 279,337 and 338 of Indian Penal Code & Sec. 134\n(A), 134 (B) of Motor Vehicle Act.\nOrder : Accused is convicted and sentenced to pay a fine of\nRs. 2,000/- for the offences U/Ss. 279,337 and 338 of\nIndian Penal Code & Sec. 134 (A), 134 (B) of Motor\nVehicle Act. In default of payment of fine the accused\nshall undergo simple imprisonment for 10 days.\nHeard, perused the records and passed the following:\nJUDGMENT\n1. The accused stands charge sheeted by the Sub Inspector of Police, Museum Police\nStation alleging offence U/Ss. 279,337 and 338 of Indian Penal Code & Sec. 134\n(A), 134 (B) of Motor Vehicle Act.\n2. Accused pleaded guilty through counsel . Particulars of offence U/Ss. 279,337 and\n\n2\n338 of Indian Penal Code & Sec. 134 (A), 134 (B) of Motor Vehicle Act\nwas read over and explained to the accused and he pleaded guilty. This\ncourt is convinced that the plea of the accused is voluntary. Hence his plea\nis accepted. The accused is found guilty for the offence U/S. 279,337 and\n338 of Indian Penal Code & Sec. 134 (A), 134 (B) of Motor Vehicle Act\nand he is convicted thereunder.\n\n3. Accused is convicted and sentenced to pay a fine of Rs. 2,000/- for the\noffences U/Ss279,337 and 338 of Indian Penal Code & Sec. 134 (A), 134\n(B) of Motor Vehicle Act. In default of payment of fine the accused shall\nundergo simple imprisonment for 10 days.\n\n(Dictated to the Confidential Assistant, transcribed and typed by her, corrected and\npronounced by me, in open court, on this the 15\" day of February, 2025.)\n\nJudicial Magistrate of the First Class- ITI\n\nThiruvananthapuram\n\n"
}